changedetection_tui/__init__.py
changedetection_tui/__main__.py
changedetection_tui/app.py
changedetection_tui/dashboard/__init__.py
changedetection_tui/dashboard/buttons.py
changedetection_tui/dashboard/dashboard.py
changedetection_tui/dashboard/diff_widgets.py
changedetection_tui/dashboard/header.py
changedetection_tui/dashboard/jump_overlay.py
changedetection_tui/dashboard/jumper.py
changedetection_tui/dashboard/pager.py
changedetection_tui/dashboard/watchlist.py
changedetection_tui/dashboard/watchrow.py
changedetection_tui/main_screen.py
changedetection_tui/settings/__init__.py
changedetection_tui/settings/kb_report.py
changedetection_tui/settings/locations.py
changedetection_tui/settings/settings.py
changedetection_tui/settings/settings_screen.py
changedetection_tui/theme.py
changedetection_tui/tui.scss
changedetection_tui/types.py
changedetection_tui/utils.py
changedetection_tui-1.0.0.dist-info/WHEEL
changedetection_tui-1.0.0.dist-info/entry_points.txt
changedetection_tui-1.0.0.dist-info/METADATA
changedetection_tui-1.0.0.dist-info/RECORD
