Metadata-Version: 2.4
Name: changedetection-tui
Version: 1.0.0
Summary: TUI client for changedetection.io
Keywords: console,tui,textual,changedetection,change,detection
Author: Giuseppe Rota
Author-email: Giuseppe Rota <403432+grota@users.noreply.github.com>
License-Expression: MIT
Classifier: Environment :: Console
Classifier: Intended Audience :: Developers
Classifier: Intended Audience :: System Administrators
Classifier: Operating System :: POSIX :: Linux
Classifier: Programming Language :: Python :: 3
Classifier: Programming Language :: Python :: 3.10
Classifier: Programming Language :: Python :: 3.11
Classifier: Programming Language :: Python :: 3.12
Classifier: Programming Language :: Python :: 3.13
Classifier: Development Status :: 4 - Beta
Requires-Dist: click>=8.2.1
Requires-Dist: httpx>=0.28.1
Requires-Dist: icdiff>=2.0.7
Requires-Dist: pathvalidate>=3.3.1
Requires-Dist: pydantic>=2.11.7
Requires-Dist: pydantic-settings[yaml]>=2.11.0
Requires-Dist: textual>=5.3.0
Requires-Dist: typing-extensions>=4.15.0
Requires-Dist: xdg-base-dirs>=6.0.2
Requires-Python: >=3.10
Project-URL: Documentation, https://github.com/grota/changedetection-tui
Project-URL: Homepage, https://github.com/grota/changedetection-tui
Project-URL: Issues, https://github.com/grota/changedetection-tui/issues
Project-URL: Repository, https://github.com/grota/changedetection-tui
